cubicweb_tag/__init__.py
cubicweb_tag/__pkginfo__.py
cubicweb_tag/entities.py
cubicweb_tag/hooks.py
cubicweb_tag/schema.py
cubicweb_tag/views.py
cubicweb_tag/data/cubes.tag.merge.js
cubicweb_tag/data/jquery.tagcloud.js
cubicweb_tag/doc/screenshot_tags_box.png
cubicweb_tag/doc/screenshot_tags_cloud_box.png
cubicweb_tag/i18n/en.po
cubicweb_tag/i18n/fr.po
cubicweb_tag/migration/1.0.2_Any.py
cubicweb_tag/migration/postcreate.py
cubicweb_tag-3.1.1.dist-info/METADATA
cubicweb_tag-3.1.1.dist-info/WHEEL
cubicweb_tag-3.1.1.dist-info/entry_points.txt
cubicweb_tag-3.1.1.dist-info/top_level.txt
cubicweb_tag-3.1.1.dist-info/RECORD
